README.txt
setup.py
src/rsl/__init__.py
src/rsl.upnp.egg-info/PKG-INFO
src/rsl.upnp.egg-info/SOURCES.txt
src/rsl.upnp.egg-info/dependency_links.txt
src/rsl.upnp.egg-info/entry_points.txt
src/rsl.upnp.egg-info/namespace_packages.txt
src/rsl.upnp.egg-info/requires.txt
src/rsl.upnp.egg-info/top_level.txt
src/rsl/upnp/__init__.py
src/rsl/upnp/descr.py
src/rsl/upnp/factories.py
src/rsl/upnp/interfaces.py
src/rsl/upnp/namespace.py
src/rsl/upnp/proxy.py
src/rsl/upnp/serializer.py
